lunation/__init__.py
lunation/main.py
lunation/sun.py
lunation-0.0.3.dist-info/LICENSE
lunation-0.0.3.dist-info/METADATA
lunation-0.0.3.dist-info/WHEEL
lunation-0.0.3.dist-info/top_level.txt
lunation-0.0.3.dist-info/RECORD
