Metadata-Version: 2.1
Name: lunation
Version: 0.0.3
Summary: python package for lunar information
Home-page: https://github.com/PyndyalaCoder/lunation
Author: Siddhu Pendyala
Author-email: elcientifico.pendyala@hotmail.com
License: MIT
Project-URL: Bug Tracker, https://github.com/PyndyalaCoder/lunation/issues
License-File: LICENSE
Requires-Dist: requests
Requires-Dist: math
